odoo/addons/sale_milestone_profile_invoicing/README.rst
odoo/addons/sale_milestone_profile_invoicing/__init__.py
odoo/addons/sale_milestone_profile_invoicing/__manifest__.py
odoo/addons/sale_milestone_profile_invoicing/i18n/ca.po
odoo/addons/sale_milestone_profile_invoicing/i18n/de.po
odoo/addons/sale_milestone_profile_invoicing/i18n/es.po
odoo/addons/sale_milestone_profile_invoicing/i18n/sale_milestone_profile_invoicing.pot
odoo/addons/sale_milestone_profile_invoicing/i18n/sl.po
odoo/addons/sale_milestone_profile_invoicing/i18n/zh_CN.po
odoo/addons/sale_milestone_profile_invoicing/models/__init__.py
odoo/addons/sale_milestone_profile_invoicing/models/sale_order_line.py
odoo/addons/sale_milestone_profile_invoicing/readme/CONFIGURE.rst
odoo/addons/sale_milestone_profile_invoicing/readme/CONTRIBUTORS.rst
odoo/addons/sale_milestone_profile_invoicing/readme/DESCRIPTION.rst
odoo/addons/sale_milestone_profile_invoicing/readme/USAGE.rst
odoo/addons/sale_milestone_profile_invoicing/static/description/icon.png
odoo/addons/sale_milestone_profile_invoicing/static/description/index.html
odoo/addons/sale_milestone_profile_invoicing/tests/__init__.py
odoo/addons/sale_milestone_profile_invoicing/tests/test_sale_milestone_profile_invoicing.py
odoo/addons/sale_milestone_profile_invoicing/views/sale_milestone_profile_invoicing.xml
odoo12_addon_sale_milestone_profile_invoicing-12.0.1.0.2.dist-info/METADATA
odoo12_addon_sale_milestone_profile_invoicing-12.0.1.0.2.dist-info/WHEEL
odoo12_addon_sale_milestone_profile_invoicing-12.0.1.0.2.dist-info/top_level.txt
odoo12_addon_sale_milestone_profile_invoicing-12.0.1.0.2.dist-info/RECORD
